whirly/__init__.py
whirly/fourier.py
whirly/integrators.py
whirly/solvers.py
whirly/utils.py
whirly/visuals.py
whirly-1.0.1.dist-info/LICENSE
whirly-1.0.1.dist-info/WHEEL
whirly-1.0.1.dist-info/METADATA
whirly-1.0.1.dist-info/RECORD
