Metadata-Version: 2.1
Name: whirly
Version: 1.0.1
Summary: Spectral solutions to two-dimensional PDEs.
Author-email: Dave Connelly <dsconnelly@nyu.edu>
Classifier: License :: OSI Approved :: MIT License
Requires-Dist: matplotlib
Requires-Dist: numpy
Project-URL: Home, https://github.com/dsconnelly/whirly
